cxmate/__init__.py
cxmate/cxmate_pb2.py
cxmate/cxmate_pb2_grpc.py
cxmate/service.py
cxmate/service_test.py
cxmate-0.15.0.dist-info/DESCRIPTION.rst
cxmate-0.15.0.dist-info/METADATA
cxmate-0.15.0.dist-info/RECORD
cxmate-0.15.0.dist-info/WHEEL
cxmate-0.15.0.dist-info/metadata.json
cxmate-0.15.0.dist-info/top_level.txt
