Metadata-Version: 2.0
Name: cxmate
Version: 0.15.0
Summary: SDK for creating cxMate services
Home-page: https://github.com/cxmate/cxmate-py
Author: Eric Sage, Brett Settle
Author-email: eric.david.sage@gmail.com
License: MIT
Keywords: cytoscape networkx network biology cxmate
Platform: UNKNOWN
Classifier: Development Status :: 3 - Alpha
Classifier: Intended Audience :: Developers
Classifier: Topic :: Software Development :: Build Tools
Classifier: License :: OSI Approved :: MIT License
Classifier: Programming Language :: Python :: 2
Classifier: Programming Language :: Python :: 2.7
Classifier: Programming Language :: Python :: 3
Requires-Dist: grpcio
Requires-Dist: networkx (==1.11)
